LICENSE
MANIFEST.in
README.md
setup.py
celmech/__init__.py
celmech/c_poisson_series.py
celmech/canonical_transformations.py
celmech/disturbing_function.py
celmech/hamiltonian.py
celmech/lie_transformations.py
celmech/maps.py
celmech/miscellaneous.py
celmech/multiplanet_hamiltonian.py
celmech/nbody_simulation_utilities.py
celmech/numerical_resonance_models.py
celmech/numerical_resonance_utils.py
celmech/planar_poincare.py
celmech/poincare.py
celmech/poisson_series.py
celmech/resonances.py
celmech/rk_integrator.py
celmech/secular.py
celmech/symplectic_evolution_operators.py
celmech/transformations.py
celmech.egg-info/PKG-INFO
celmech.egg-info/SOURCES.txt
celmech.egg-info/dependency_links.txt
celmech.egg-info/not-zip-safe
celmech.egg-info/requires.txt
celmech.egg-info/top_level.txt
src/disturbing_function.c
src/fmft.c
src/fmftPy.c
src/nrutil.c
src/nrutil.h
src/poincare.c
src/poisson_series.c
src/poisson_series.h