Metadata-Version: 2.1
Name: celmech
Version: 1.5.4
Summary: Open source tools for celestial mechanics
Home-page: http://github.com/shadden/celmech
Author: Dan Tamayo, Sam Hadden
Author-email: tamayo.daniel@gmail.com, shadden1107@gmail.com
License: GPL
Keywords: astronomy astrophysics celestial-mechanics orbits orbital-mechanics
Classifier: Development Status :: 3 - Alpha
Classifier: Intended Audience :: Science/Research
Classifier: Intended Audience :: Developers
Classifier: Topic :: Software Development :: Build Tools
Classifier: Topic :: Scientific/Engineering :: Astronomy
Classifier: License :: OSI Approved :: GNU General Public License v3 or later (GPLv3+)
Classifier: Programming Language :: Python :: 2
Classifier: Programming Language :: Python :: 3
License-File: LICENSE
Requires-Dist: exoplanet-core>=0.3.0rc2
Requires-Dist: pytensor>=2.18
Requires-Dist: mpmath>=1.0.0
Requires-Dist: sympy>=1.1.1
Requires-Dist: rebound>=4.0.1
Requires-Dist: reboundx>=4.0.0
Requires-Dist: numpy
Requires-Dist: scipy>=1.2.0
